dingle/__init__.py
dingle/cmd.py
dingle/interface.py
dingle/ldap_server.py
dingle/core/__init__.py
dingle/core/token.py
dingle/dingtalk/__init__.py
dingle/dingtalk/auth.py
dingle/dingtalk/blackboard.py
dingle/dingtalk/call_back.py
dingle/dingtalk/chat.py
dingle/dingtalk/department.py
dingle/dingtalk/file.py
dingle/dingtalk/message.py
dingle/dingtalk/models.py
dingle/dingtalk/process.py
dingle/dingtalk/role.py
dingle/dingtalk/user.py
dingle/util/__init__.py
dingle/util/api.py
dingle/util/conf.py
dingle/util/crypto.py
dingle/util/data_store.py
dingle/util/decr.py
dingle/util/log.py
dingle-0.0.3.dist-info/LICENSE
dingle-0.0.3.dist-info/METADATA
dingle-0.0.3.dist-info/WHEEL
dingle-0.0.3.dist-info/entry_points.txt
dingle-0.0.3.dist-info/top_level.txt
dingle-0.0.3.dist-info/RECORD
