Metadata-Version: 2.1
Name: dingle
Version: 0.0.3
Summary: UNKNOWN
Home-page: https://github.com/gstianfu/dingle
Author: gstianfu
Author-email: UNKNOWN
License: UNKNOWN
Platform: UNKNOWN
Classifier: Environment :: Console
Classifier: Intended Audience :: Developers
Classifier: License :: OSI Approved :: Apache Software License
Classifier: Programming Language :: Python
Requires-Dist: six
